linkguard/__init__.py
linkguard/cli.py
linkguard/reporter/__init__.py
linkguard/reporter/exporter.py
linkguard/reporter/formatter.py
linkguard/scanner/__init__.py
linkguard/scanner/file_scanner.py
linkguard/scanner/link_checker.py
linkguard/scanner/rules.py
linkguard/scanner/url_extractor.py
linkguard/utils/__init__.py
linkguard/utils/config.py
linkguard/utils/logger.py
linkguard-1.0.1.dist-info/METADATA
linkguard-1.0.1.dist-info/WHEEL
linkguard-1.0.1.dist-info/entry_points.txt
linkguard-1.0.1.dist-info/top_level.txt
linkguard-1.0.1.dist-info/RECORD
