Metadata-Version: 2.4
Name: linkguard
Version: 1.0.1
Summary: CLI tool for detecting broken links and localhost URLs in project files
Author-email: Anubhab Debnath <anubhabxdev@gmail.com>
Maintainer-email: Anubhab Debnath <anubhabxdev@gmail.com>
Project-URL: Homepage, https://github.com/anubhabx/link-guard
Project-URL: Documentation, https://github.com/anubhabx/link-guard#readme
Project-URL: Repository, https://github.com/anubhabx/link-guard
Project-URL: Issues, https://github.com/anubhabx/link-guard/issues
Project-URL: Changelog, https://github.com/anubhabx/link-guard/releases
Keywords: link-checker,broken-links,url-validator,markdown,documentation,ci-cd,async,cli
Classifier: Development Status :: 5 - Production/Stable
Classifier: Intended Audience :: Developers
Classifier: Topic :: Software Development :: Quality Assurance
Classifier: Topic :: Software Development :: Documentation
Classifier: Programming Language :: Python :: 3
Classifier: Programming Language :: Python :: 3.10
Classifier: Programming Language :: Python :: 3.11
Classifier: Programming Language :: Python :: 3.12
Classifier: Environment :: Console
Classifier: Operating System :: OS Independent
Classifier: Typing :: Typed
Requires-Python: >=3.10
Requires-Dist: typer>=0.9.0
Requires-Dist: rich>=13.0.0
Requires-Dist: aiohttp>=3.9.0
Requires-Dist: beautifulsoup4>=4.12.0
Requires-Dist: brotli>=1.1.0
Provides-Extra: dev
Requires-Dist: pytest>=7.4.0; extra == "dev"
Requires-Dist: pytest-asyncio>=0.21.0; extra == "dev"
Requires-Dist: pytest-cov>=4.1.0; extra == "dev"
Requires-Dist: black>=23.0.0; extra == "dev"
Requires-Dist: flake8>=6.0.0; extra == "dev"
Requires-Dist: mypy>=1.5.0; extra == "dev"
Requires-Dist: pre-commit>=3.3.0; extra == "dev"
